repobee_feedback/__init__.py
repobee_feedback/__version.py
repobee_feedback/_generate_multi_issues_file.py
repobee_feedback/feedback.py
repobee_feedback-0.7.0.dist-info/LICENSE
repobee_feedback-0.7.0.dist-info/METADATA
repobee_feedback-0.7.0.dist-info/WHEEL
repobee_feedback-0.7.0.dist-info/top_level.txt
repobee_feedback-0.7.0.dist-info/RECORD
