Metadata-Version: 2.1
Name: repobee-feedback
Version: 0.7.0
Summary: A plugin that adds the issue-feedback command to RepoBee
Home-page: https://github.com/slarse/repobee-feedback
Author: Simon Larsén
Author-email: slarse@kth.se
License: MIT
Download-URL: https://github.com/slarse/repobee-feedback/archive/v0.7.0.tar.gz
Platform: UNKNOWN
Classifier: Development Status :: 3 - Alpha
Classifier: Intended Audience :: Education
Classifier: Programming Language :: Python :: 3.7
Classifier: Programming Language :: Python :: 3.8
Classifier: Programming Language :: Python :: Implementation :: CPython
Classifier: License :: OSI Approved :: MIT License
Classifier: Operating System :: POSIX
Requires-Python: >=3.7
Requires-Dist: repobee (>=3.0.0-beta.1)
Provides-Extra: test
Requires-Dist: pytest ; extra == 'test'
Requires-Dist: pytest-cov ; extra == 'test'
Requires-Dist: repobee ; extra == 'test'
Requires-Dist: codecov ; extra == 'test'
Requires-Dist: black ; extra == 'test'
Requires-Dist: flake8 ; extra == 'test'
Requires-Dist: mypy ; extra == 'test'
Requires-Dist: types-dataclasses ; (python_version < "3.7") and extra == 'test'
